{
  "generated_at": "2026-04-22T23:06:13+00:00",
  "window_date": "2026-03-30",
  "status": "ok",
  "n_games": 15,
  "games": {
    "824135": {
      "n_sims": 10000,
      "away_team": "Minnesota Twins",
      "home_team": "Kansas City Royals",
      "actual_away_runs": 1,
      "actual_home_runs": 3,
      "sim_away_mean": 5.335112,
      "sim_home_mean": 6.1203030000000025,
      "sim_away_median": 5.31,
      "sim_home_median": 6.120000000000003,
      "away_win_prob": 0.36695,
      "home_win_prob": 0.63305,
      "p_away_wins_exactly": 0.3668,
      "p_home_wins_exactly": 0.6329,
      "p_tied": 0.0003,
      "ump_favor_away_runs": 0.0,
      "ump_favor_home_runs": 0.0,
      "ump_adjusted_away_mean": 5.335112,
      "ump_adjusted_home_mean": 6.1203030000000025,
      "ump_adjusted_away_wp": 0.36695,
      "ump_adjusted_home_wp": 0.63305,
      "wp_shift_away": 0.0,
      "umpire_name": "Alex Tosi",
      "venue": "Kauffman Stadium",
      "n_batted_balls": 46
    },
    "824863": {
      "n_sims": 10000,
      "away_team": "Texas Rangers",
      "home_team": "Baltimore Orioles",
      "actual_away_runs": 5,
      "actual_home_runs": 2,
      "sim_away_mean": 7.112494,
      "sim_home_mean": 5.935130999999998,
      "sim_away_median": 7.119999999999999,
      "sim_home_median": 5.93,
      "away_win_prob": 0.6962499999999999,
      "home_win_prob": 0.3037500000000001,
      "p_away_wins_exactly": 0.6959,
      "p_home_wins_exactly": 0.3034,
      "p_tied": 0.0007,
      "ump_favor_away_runs": 0.0,
      "ump_favor_home_runs": 0.0,
      "ump_adjusted_away_mean": 7.112494,
      "ump_adjusted_home_mean": 5.935130999999998,
      "ump_adjusted_away_wp": 0.6962499999999999,
      "ump_adjusted_home_wp": 0.3037500000000001,
      "wp_shift_away": 0.0,
      "umpire_name": "Ron Kulpa",
      "venue": "Oriole Park at Camden Yards",
      "n_batted_balls": 50
    },
    "824539": {
      "n_sims": 10000,
      "away_team": "Pittsburgh Pirates",
      "home_team": "Cincinnati Reds",
      "actual_away_runs": 0,
      "actual_home_runs": 2,
      "sim_away_mean": 3.5495880000000004,
      "sim_home_mean": 5.569543,
      "sim_away_median": 3.619999999999999,
      "sim_home_median": 5.559999999999999,
      "away_win_prob": 0.14445,
      "home_win_prob": 0.85555,
      "p_away_wins_exactly": 0.1439,
      "p_home_wins_exactly": 0.855,
      "p_tied": 0.0011,
      "ump_favor_away_runs": 0.0,
      "ump_favor_home_runs": 0.0,
      "ump_adjusted_away_mean": 3.5495880000000004,
      "ump_adjusted_home_mean": 5.569543,
      "ump_adjusted_away_wp": 0.14445,
      "ump_adjusted_home_wp": 0.85555,
      "wp_shift_away": 0.0,
      "umpire_name": "Junior Valentine",
      "venue": "Great American Ball Park",
      "n_batted_balls": 39
    },
    "823484": {
      "n_sims": 10000,
      "away_team": "Washington Nationals",
      "home_team": "Philadelphia Phillies",
      "actual_away_runs": 13,
      "actual_home_runs": 2,
      "sim_away_mean": 13.542822000000003,
      "sim_home_mean": 4.780331000000001,
      "sim_away_median": 13.500000000000004,
      "sim_home_median": 4.8100000000000005,
      "away_win_prob": 1.0,
      "home_win_prob": 0.0,
      "p_away_wins_exactly": 1.0,
      "p_home_wins_exactly": 0.0,
      "p_tied": 0.0,
      "ump_favor_away_runs": 0.0,
      "ump_favor_home_runs": 0.0,
      "ump_adjusted_away_mean": 13.542822000000003,
      "ump_adjusted_home_mean": 4.780331000000001,
      "ump_adjusted_away_wp": 1.0,
      "ump_adjusted_home_wp": 0.0,
      "wp_shift_away": 0.0,
      "umpire_name": "Nick Mahrley",
      "venue": "Citizens Bank Park",
      "n_batted_balls": 65
    },
    "823890": {
      "n_sims": 10000,
      "away_team": "Chicago White Sox",
      "home_team": "Miami Marlins",
      "actual_away_runs": 9,
      "actual_home_runs": 4,
      "sim_away_mean": 11.506308000000002,
      "sim_home_mean": 5.273655000000001,
      "sim_away_median": 11.505000000000003,
      "sim_home_median": 5.250000000000001,
      "away_win_prob": 0.9951,
      "home_win_prob": 0.0049000000000000155,
      "p_away_wins_exactly": 0.9951,
      "p_home_wins_exactly": 0.0049,
      "p_tied": 0.0,
      "ump_favor_away_runs": 0.0,
      "ump_favor_home_runs": 0.0,
      "ump_adjusted_away_mean": 11.506308000000002,
      "ump_adjusted_home_mean": 5.273655000000001,
      "ump_adjusted_away_wp": 0.9951,
      "ump_adjusted_home_wp": 0.0049000000000000155,
      "wp_shift_away": 0.0,
      "umpire_name": "Emil Jimenez",
      "venue": "loanDepot park",
      "n_batted_balls": 47
    },
    "822834": {
      "n_sims": 10000,
      "away_team": "Colorado Rockies",
      "home_team": "Toronto Blue Jays",
      "actual_away_runs": 14,
      "actual_home_runs": 5,
      "sim_away_mean": 13.068562000000002,
      "sim_home_mean": 7.443641999999999,
      "sim_away_median": 13.07,
      "sim_home_median": 7.449999999999999,
      "away_win_prob": 0.9773,
      "home_win_prob": 0.022700000000000053,
      "p_away_wins_exactly": 0.9773,
      "p_home_wins_exactly": 0.0227,
      "p_tied": 0.0,
      "ump_favor_away_runs": 0.0,
      "ump_favor_home_runs": 0.0,
      "ump_adjusted_away_mean": 13.068562000000002,
      "ump_adjusted_home_mean": 7.443641999999999,
      "ump_adjusted_away_wp": 0.9773,
      "ump_adjusted_home_wp": 0.022700000000000053,
      "wp_shift_away": 0.0,
      "umpire_name": "Erich Bacchus",
      "venue": "Rogers Centre",
      "n_batted_balls": 60
    },
    "824943": {
      "n_sims": 10000,
      "away_team": "Athletics",
      "home_team": "Atlanta Braves",
      "actual_away_runs": 0,
      "actual_home_runs": 4,
      "sim_away_mean": 2.2527190000000004,
      "sim_home_mean": 6.222942000000001,
      "sim_away_median": 2.1900000000000004,
      "sim_home_median": 6.25,
      "away_win_prob": 0.0298,
      "home_win_prob": 0.9702,
      "p_away_wins_exactly": 0.0298,
      "p_home_wins_exactly": 0.9702,
      "p_tied": 0.0,
      "ump_favor_away_runs": 0.0,
      "ump_favor_home_runs": 0.0,
      "ump_adjusted_away_mean": 2.2527190000000004,
      "ump_adjusted_home_mean": 6.222942000000001,
      "ump_adjusted_away_wp": 0.0298,
      "ump_adjusted_home_wp": 0.9702,
      "wp_shift_away": 0.0,
      "umpire_name": "Dan Bellino",
      "venue": "Truist Park",
      "n_batted_balls": 53
    },
    "824702": {
      "n_sims": 10000,
      "away_team": "Los Angeles Angels",
      "home_team": "Chicago Cubs",
      "actual_away_runs": 2,
      "actual_home_runs": 7,
      "sim_away_mean": 5.4407739999999984,
      "sim_home_mean": 9.944326,
      "sim_away_median": 5.429999999999998,
      "sim_home_median": 9.94,
      "away_win_prob": 0.0186,
      "home_win_prob": 0.9814,
      "p_away_wins_exactly": 0.0186,
      "p_home_wins_exactly": 0.9814,
      "p_tied": 0.0,
      "ump_favor_away_runs": 0.0,
      "ump_favor_home_runs": 0.0,
      "ump_adjusted_away_mean": 5.4407739999999984,
      "ump_adjusted_home_mean": 9.944326,
      "ump_adjusted_away_wp": 0.0186,
      "ump_adjusted_home_wp": 0.9814,
      "wp_shift_away": 0.0,
      "umpire_name": "Charlie Ramos",
      "venue": "Wrigley Field",
      "n_batted_balls": 49
    },
    "823809": {
      "n_sims": 10000,
      "away_team": "Tampa Bay Rays",
      "home_team": "Milwaukee Brewers",
      "actual_away_runs": 3,
      "actual_home_runs": 2,
      "sim_away_mean": 4.363562,
      "sim_home_mean": 5.222554000000001,
      "sim_away_median": 4.379999999999999,
      "sim_home_median": 5.1899999999999995,
      "away_win_prob": 0.3554,
      "home_win_prob": 0.6446000000000001,
      "p_away_wins_exactly": 0.3509,
      "p_home_wins_exactly": 0.6401,
      "p_tied": 0.009,
      "ump_favor_away_runs": 0.0,
      "ump_favor_home_runs": 0.0,
      "ump_adjusted_away_mean": 4.363562,
      "ump_adjusted_home_mean": 5.222554000000001,
      "ump_adjusted_away_wp": 0.3554,
      "ump_adjusted_home_wp": 0.6446000000000001,
      "wp_shift_away": 0.0,
      "umpire_name": "Jeremie Rehak",
      "venue": "American Family Field",
      "n_batted_balls": 45
    },
    "823080": {
      "n_sims": 10000,
      "away_team": "New York Mets",
      "home_team": "St. Louis Cardinals",
      "actual_away_runs": 4,
      "actual_home_runs": 2,
      "sim_away_mean": 7.012718,
      "sim_home_mean": 5.679950999999998,
      "sim_away_median": 7.0,
      "sim_home_median": 5.619999999999998,
      "away_win_prob": 0.7133,
      "home_win_prob": 0.28669999999999995,
      "p_away_wins_exactly": 0.7133,
      "p_home_wins_exactly": 0.2867,
      "p_tied": 0.0,
      "ump_favor_away_runs": 0.0,
      "ump_favor_home_runs": 0.0,
      "ump_adjusted_away_mean": 7.012718,
      "ump_adjusted_home_mean": 5.679950999999998,
      "ump_adjusted_away_wp": 0.7133,
      "ump_adjusted_home_wp": 0.28669999999999995,
      "wp_shift_away": 0.0,
      "umpire_name": "Vic Carapazza",
      "venue": "Busch Stadium",
      "n_batted_balls": 54
    },
    "824214": {
      "n_sims": 10000,
      "away_team": "Boston Red Sox",
      "home_team": "Houston Astros",
      "actual_away_runs": 1,
      "actual_home_runs": 8,
      "sim_away_mean": 3.2500199999999997,
      "sim_home_mean": 7.1340419999999956,
      "sim_away_median": 3.19,
      "sim_home_median": 7.139999999999997,
      "away_win_prob": 0.0507,
      "home_win_prob": 0.9493,
      "p_away_wins_exactly": 0.0507,
      "p_home_wins_exactly": 0.9493,
      "p_tied": 0.0,
      "ump_favor_away_runs": 0.0,
      "ump_favor_home_runs": 0.0,
      "ump_adjusted_away_mean": 3.2500199999999997,
      "ump_adjusted_home_mean": 7.1340419999999956,
      "ump_adjusted_away_wp": 0.0507,
      "ump_adjusted_home_wp": 0.9493,
      "wp_shift_away": 0.0,
      "umpire_name": "Nate Tomlinson",
      "venue": "Daikin Park",
      "n_batted_balls": 46
    },
    "823320": {
      "n_sims": 10000,
      "away_team": "San Francisco Giants",
      "home_team": "San Diego Padres",
      "actual_away_runs": 3,
      "actual_home_runs": 2,
      "sim_away_mean": 6.299732,
      "sim_home_mean": 5.0470299999999995,
      "sim_away_median": 6.31,
      "sim_home_median": 5.0,
      "away_win_prob": 0.73195,
      "home_win_prob": 0.26805,
      "p_away_wins_exactly": 0.7289,
      "p_home_wins_exactly": 0.265,
      "p_tied": 0.0061,
      "ump_favor_away_runs": 0.0,
      "ump_favor_home_runs": 0.0,
      "ump_adjusted_away_mean": 6.299732,
      "ump_adjusted_home_mean": 5.0470299999999995,
      "ump_adjusted_away_wp": 0.73195,
      "ump_adjusted_home_wp": 0.26805,
      "wp_shift_away": 0.0,
      "umpire_name": "Lance Barksdale",
      "venue": "Petco Park",
      "n_batted_balls": 43
    },
    "823159": {
      "n_sims": 10000,
      "away_team": "New York Yankees",
      "home_team": "Seattle Mariners",
      "actual_away_runs": 1,
      "actual_home_runs": 2,
      "sim_away_mean": 2.8224269999999985,
      "sim_home_mean": 3.350490999999999,
      "sim_away_median": 2.8099999999999983,
      "sim_home_median": 3.3099999999999996,
      "away_win_prob": 0.3801,
      "home_win_prob": 0.6199,
      "p_away_wins_exactly": 0.3796,
      "p_home_wins_exactly": 0.6194,
      "p_tied": 0.001,
      "ump_favor_away_runs": 0.0,
      "ump_favor_home_runs": 0.0,
      "ump_adjusted_away_mean": 2.8224269999999985,
      "ump_adjusted_home_mean": 3.350490999999999,
      "ump_adjusted_away_wp": 0.3801,
      "ump_adjusted_home_wp": 0.6199,
      "wp_shift_away": 0.0,
      "umpire_name": "Mike Estabrook",
      "venue": "T-Mobile Park",
      "n_batted_balls": 46
    },
    "825108": {
      "n_sims": 10000,
      "away_team": "Detroit Tigers",
      "home_team": "Arizona Diamondbacks",
      "actual_away_runs": 6,
      "actual_home_runs": 9,
      "sim_away_mean": 7.449197,
      "sim_home_mean": 12.077382000000002,
      "sim_away_median": 7.430000000000001,
      "sim_home_median": 12.060000000000002,
      "away_win_prob": 0.0423,
      "home_win_prob": 0.9577,
      "p_away_wins_exactly": 0.0423,
      "p_home_wins_exactly": 0.9577,
      "p_tied": 0.0,
      "ump_favor_away_runs": 0.0,
      "ump_favor_home_runs": 0.0,
      "ump_adjusted_away_mean": 7.449197,
      "ump_adjusted_home_mean": 12.077382000000002,
      "ump_adjusted_away_wp": 0.0423,
      "ump_adjusted_home_wp": 0.9577,
      "wp_shift_away": 0.0,
      "umpire_name": "Todd Tichenor",
      "venue": "Chase Field",
      "n_batted_balls": 56
    },
    "823972": {
      "n_sims": 10000,
      "away_team": "Cleveland Guardians",
      "home_team": "Los Angeles Dodgers",
      "actual_away_runs": 4,
      "actual_home_runs": 2,
      "sim_away_mean": 6.614011000000001,
      "sim_home_mean": 4.6487870000000004,
      "sim_away_median": 6.620000000000001,
      "sim_home_median": 4.619999999999999,
      "away_win_prob": 0.82195,
      "home_win_prob": 0.17805000000000004,
      "p_away_wins_exactly": 0.8218,
      "p_home_wins_exactly": 0.1779,
      "p_tied": 0.0003,
      "ump_favor_away_runs": 0.0,
      "ump_favor_home_runs": 0.0,
      "ump_adjusted_away_mean": 6.614011000000001,
      "ump_adjusted_home_mean": 4.6487870000000004,
      "ump_adjusted_away_wp": 0.82195,
      "ump_adjusted_home_wp": 0.17805000000000004,
      "wp_shift_away": 0.0,
      "umpire_name": "Paul Clemons",
      "venue": "UNIQLO Field at Dodger Stadium",
      "n_batted_balls": 55
    }
  }
}