{
  "generated_at": "2026-04-23T18:31:10.464Z",
  "date": "2026-03-27",
  "source": "Action Network projections page (authed, browser-scraped) \u00b7 MLB Stats API for scores/game_pk",
  "note": "ML + Total markets, Open + Consensus + PRO projections. PRO = AN model (devigged projection odds, letter grade, edge %).",
  "n_games": 8,
  "n_with_game_pk": 8,
  "games": [
    {
      "away_team": "Rockies",
      "home_team": "Marlins",
      "away_rot": "965",
      "home_rot": "966",
      "game_pk": 823893,
      "status": "Final",
      "actual_away_runs": 1,
      "actual_home_runs": 2,
      "open": {
        "ml_away": 140,
        "ml_home": -165,
        "total": {
          "line": 8.5
        }
      },
      "consensus": {
        "ml_away": 164,
        "ml_home": -199,
        "total": {
          "line": 7.5
        }
      },
      "pro": {
        "ml_away_proj": 151,
        "ml_home_proj": -151,
        "ml_away_grade": "C",
        "ml_home_grade": "D-",
        "ml_away_edge_pct": 1.5,
        "ml_home_edge_pct": -5.8,
        "over_proj": 7.63,
        "under_proj": 7.63,
        "over_grade": "D",
        "under_grade": "D+",
        "over_edge_pct": -3.5,
        "under_edge_pct": -1.1
      },
      "best_odds": {
        "ml": [
          "+164",
          "-190"
        ],
        "total": [
          "o8",
          "-104",
          "u7.5",
          "+102"
        ]
      },
      "bet_pct": {
        "ml": [
          "12%",
          "88%"
        ],
        "total": [
          "94%",
          "6%"
        ]
      },
      "money_pct": {
        "ml": [
          "21%",
          "79%"
        ],
        "total": [
          "93%",
          "7%"
        ]
      }
    },
    {
      "away_team": "Royals",
      "home_team": "Braves",
      "away_rot": "977",
      "home_rot": "978",
      "game_pk": 824946,
      "status": "Final",
      "actual_away_runs": 0,
      "actual_home_runs": 6,
      "open": {
        "ml_away": 125,
        "ml_home": -150,
        "total": {
          "line": 8
        }
      },
      "consensus": {
        "ml_away": 119,
        "ml_home": -141,
        "total": {
          "line": 7.5
        }
      },
      "pro": {
        "ml_away_proj": 145,
        "ml_home_proj": -145,
        "ml_away_grade": "D-",
        "ml_home_grade": "C",
        "ml_away_edge_pct": -5,
        "ml_home_edge_pct": 0.9,
        "over_proj": 7.31,
        "under_proj": 7.31,
        "over_grade": "D-",
        "under_grade": "C-",
        "over_edge_pct": -4.9,
        "under_edge_pct": 0.4
      },
      "best_odds": {
        "ml": [
          "+123",
          "-138"
        ],
        "total": [
          "o7.5",
          "+105",
          "u7.5",
          "-105"
        ]
      },
      "bet_pct": {
        "ml": [
          "14%",
          "86%"
        ],
        "total": [
          "90%",
          "10%"
        ]
      },
      "money_pct": {
        "ml": [
          "10%",
          "90%"
        ],
        "total": [
          "89%",
          "11%"
        ]
      }
    },
    {
      "away_team": "Athletics",
      "home_team": "Blue Jays",
      "away_rot": "969",
      "home_rot": "970",
      "game_pk": 822839,
      "status": "Final",
      "actual_away_runs": 2,
      "actual_home_runs": 3,
      "open": {
        "ml_away": 170,
        "ml_home": -210,
        "total": {
          "line": 9.5
        }
      },
      "consensus": {
        "ml_away": 147,
        "ml_home": -180,
        "total": {
          "line": 8.5
        }
      },
      "pro": {
        "ml_away_proj": 146,
        "ml_home_proj": -146,
        "ml_away_grade": "C-",
        "ml_home_grade": "D-",
        "ml_away_edge_pct": 0.5,
        "ml_home_edge_pct": -5,
        "over_proj": 9.48,
        "under_proj": 9.48,
        "over_grade": "B-",
        "under_grade": "F",
        "over_edge_pct": 3.8,
        "under_edge_pct": -8.6
      },
      "best_odds": {
        "ml": [
          "+150",
          "-169"
        ],
        "total": [
          "o8.5",
          "-118",
          "u8.5",
          "+100"
        ]
      },
      "bet_pct": {
        "ml": [
          "7%",
          "93%"
        ],
        "total": [
          "95%",
          "5%"
        ]
      },
      "money_pct": {
        "ml": [
          "8%",
          "92%"
        ],
        "total": [
          "94%",
          "6%"
        ]
      }
    },
    {
      "away_team": "Guardians",
      "home_team": "Mariners",
      "away_rot": "973",
      "home_rot": "974",
      "game_pk": 823162,
      "status": "Final",
      "actual_away_runs": 1,
      "actual_home_runs": 5,
      "open": {
        "ml_away": 145,
        "ml_home": -167,
        "total": {
          "line": 7
        }
      },
      "consensus": {
        "ml_away": 145,
        "ml_home": -174,
        "total": {
          "line": 7
        }
      },
      "pro": {
        "ml_away_proj": 173,
        "ml_home_proj": -173,
        "ml_away_grade": "D-",
        "ml_home_grade": "D+",
        "ml_away_edge_pct": -4.2,
        "ml_home_edge_pct": -0.1,
        "over_proj": 6.37,
        "under_proj": 6.37,
        "over_grade": "F",
        "under_grade": "C",
        "over_edge_pct": -6.5,
        "under_edge_pct": 1.8
      },
      "best_odds": {
        "ml": [
          "+146",
          "-167"
        ],
        "total": [
          "o7.5",
          "+110",
          "u7",
          "-110"
        ]
      },
      "bet_pct": {
        "ml": [
          "20%",
          "80%"
        ],
        "total": [
          "93%",
          "7%"
        ]
      },
      "money_pct": {
        "ml": [
          "25%",
          "75%"
        ],
        "total": [
          "85%",
          "15%"
        ]
      }
    },
    {
      "away_team": "Yankees",
      "home_team": "Giants",
      "away_rot": "975",
      "home_rot": "976",
      "game_pk": 823243,
      "status": "Final",
      "actual_away_runs": 3,
      "actual_home_runs": 0,
      "open": {
        "ml_away": -122,
        "ml_home": 104,
        "total": {
          "line": 8
        }
      },
      "consensus": {
        "ml_away": -136,
        "ml_home": 115,
        "total": {
          "line": 8.5
        }
      },
      "pro": {
        "ml_away_proj": -126,
        "ml_home_proj": 126,
        "ml_away_grade": "D+",
        "ml_home_grade": "D",
        "ml_away_edge_pct": -0.9,
        "ml_home_edge_pct": -3.4,
        "over_proj": 8.52,
        "under_proj": 8.52,
        "over_grade": "D+",
        "under_grade": "D+",
        "over_edge_pct": -2,
        "under_edge_pct": -1.4
      },
      "best_odds": {
        "ml": [
          "-130",
          "+116"
        ],
        "total": [
          "o8.5",
          "-105",
          "u8",
          "+100"
        ]
      },
      "bet_pct": {
        "ml": [
          "84%",
          "16%"
        ],
        "total": [
          "90%",
          "10%"
        ]
      },
      "money_pct": {
        "ml": [
          "84%",
          "16%"
        ],
        "total": [
          "86%",
          "14%"
        ]
      }
    },
    {
      "away_team": "Tigers",
      "home_team": "Padres",
      "away_rot": "979",
      "home_rot": "980",
      "game_pk": 823324,
      "status": "Final",
      "actual_away_runs": 5,
      "actual_home_runs": 2,
      "open": {
        "ml_away": 100,
        "ml_home": -118,
        "total": {
          "line": 7.5
        }
      },
      "consensus": {
        "ml_away": 111,
        "ml_home": -136,
        "total": {
          "line": 7.5
        }
      },
      "pro": {
        "ml_away_proj": 119,
        "ml_home_proj": -119,
        "ml_away_grade": "D+",
        "ml_home_grade": "D",
        "ml_away_edge_pct": -1.1,
        "ml_home_edge_pct": -2.5,
        "over_proj": 7.62,
        "under_proj": 7.62,
        "over_grade": "C-",
        "under_grade": "D-",
        "over_edge_pct": 0.5,
        "under_edge_pct": -5.1
      },
      "best_odds": {
        "ml": [
          "+115",
          "-130"
        ],
        "total": [
          "o7.5",
          "+104",
          "u7.5",
          "-115"
        ]
      },
      "bet_pct": {
        "ml": [
          "45%",
          "55%"
        ],
        "total": [
          "91%",
          "9%"
        ]
      },
      "money_pct": {
        "ml": [
          "32%",
          "68%"
        ],
        "total": [
          "89%",
          "11%"
        ]
      }
    },
    {
      "away_team": "Angels",
      "home_team": "Astros",
      "away_rot": "971",
      "home_rot": "972",
      "game_pk": 824216,
      "status": "Final",
      "actual_away_runs": 6,
      "actual_home_runs": 2,
      "open": {
        "ml_away": 125,
        "ml_home": -152,
        "total": {
          "line": 8.5
        }
      },
      "consensus": {
        "ml_away": 145,
        "ml_home": -172,
        "total": {
          "line": 8.5
        }
      },
      "pro": {
        "ml_away_proj": 158,
        "ml_home_proj": -158,
        "ml_away_grade": "D",
        "ml_home_grade": "D+",
        "ml_away_edge_pct": -2.6,
        "ml_home_edge_pct": -1.7,
        "over_proj": 8.95,
        "under_proj": 8.95,
        "over_grade": "D+",
        "under_grade": "D-",
        "over_edge_pct": -0.2,
        "under_edge_pct": -5
      },
      "best_odds": {
        "ml": [
          "+146",
          "-169"
        ],
        "total": [
          "o8.5",
          "-113",
          "u8.5",
          "+100"
        ]
      },
      "bet_pct": {
        "ml": [
          "20%",
          "80%"
        ],
        "total": [
          "87%",
          "13%"
        ]
      },
      "money_pct": {
        "ml": [
          "30%",
          "70%"
        ],
        "total": [
          "83%",
          "17%"
        ]
      }
    },
    {
      "away_team": "Diamondbacks",
      "home_team": "Dodgers",
      "away_rot": "967",
      "home_rot": "968",
      "game_pk": 823971,
      "status": "Final",
      "actual_away_runs": 4,
      "actual_home_runs": 5,
      "open": {
        "ml_away": 172,
        "ml_home": -205,
        "total": {
          "line": 8.5
        }
      },
      "consensus": {
        "ml_away": 196,
        "ml_home": -240,
        "total": {
          "line": 8.5
        }
      },
      "pro": {
        "ml_away_proj": 216,
        "ml_home_proj": -216,
        "ml_away_grade": "D",
        "ml_home_grade": "D",
        "ml_away_edge_pct": -2.2,
        "ml_home_edge_pct": -2.2,
        "over_proj": 9.52,
        "under_proj": 9.52,
        "over_grade": "B-",
        "under_grade": "F",
        "over_edge_pct": 3.9,
        "under_edge_pct": -9.7
      },
      "best_odds": {
        "ml": [
          "+205",
          "-240"
        ],
        "total": [
          "o9",
          "+101",
          "u8.5",
          "+100"
        ]
      },
      "bet_pct": {
        "ml": [
          "5%",
          "95%"
        ],
        "total": [
          "96%",
          "4%"
        ]
      },
      "money_pct": {
        "ml": [
          "10%",
          "90%"
        ],
        "total": [
          "96%",
          "4%"
        ]
      }
    }
  ]
}