{
  "generated_at": "2026-04-28T02:38:35.641223Z",
  "source": "MLB Stats API (statSplits + gameLog + season)",
  "season": 2026,
  "pitchers": {
    "nick martinez": {
      "pid": 607259,
      "name": "Nick Martinez",
      "hand": "R",
      "vs_r": {
        "tbf": 48,
        "k_pct": 16.7,
        "bb_pct": 2.1,
        "woba": null,
        "hr_per_pa": 2.1,
        "avg_against": ".196",
        "ops_against": ".491"
      },
      "vs_l": {
        "tbf": 74,
        "k_pct": 16.2,
        "bb_pct": 9.5,
        "woba": null,
        "hr_per_pa": 2.7,
        "avg_against": ".239",
        "ops_against": ".699"
      },
      "season_summary": {
        "games": null,
        "starts": 5,
        "ip": "30.0",
        "era": "2.10",
        "k_pct": 16.4,
        "bb_pct": 6.6
      },
      "last5_starts_avg_ip": 5.86,
      "is_opener": false,
      "opener_reason": null,
      "team": "Tampa Bay Rays",
      "game_pk": 824447
    },
    "tanner bibee": {
      "pid": 676440,
      "name": "Tanner Bibee",
      "hand": "R",
      "vs_r": {
        "tbf": 61,
        "k_pct": 18.0,
        "bb_pct": 6.6,
        "woba": null,
        "hr_per_pa": 0.0,
        "avg_against": ".316",
        "ops_against": ".747"
      },
      "vs_l": {
        "tbf": 70,
        "k_pct": 21.4,
        "bb_pct": 10.0,
        "woba": null,
        "hr_per_pa": 7.1,
        "avg_against": ".238",
        "ops_against": ".806"
      },
      "season_summary": {
        "games": null,
        "starts": 6,
        "ip": "30.1",
        "era": "4.45",
        "k_pct": 19.8,
        "bb_pct": 8.4
      },
      "last5_starts_avg_ip": 4.88,
      "is_opener": false,
      "opener_reason": null,
      "team": "Cleveland Guardians",
      "game_pk": 824447
    },
    "kai-wei teng": {
      "pid": 678906,
      "name": "Kai-Wei Teng",
      "hand": "R",
      "vs_r": {
        "tbf": 33,
        "k_pct": 24.2,
        "bb_pct": 15.2,
        "woba": null,
        "hr_per_pa": 0.0,
        "avg_against": ".143",
        "ops_against": ".416"
      },
      "vs_l": {
        "tbf": 31,
        "k_pct": 25.8,
        "bb_pct": 3.2,
        "woba": null,
        "hr_per_pa": 9.7,
        "avg_against": ".167",
        "ops_against": ".661"
      },
      "season_summary": {
        "games": null,
        "starts": 0,
        "ip": "16.2",
        "era": "2.16",
        "k_pct": 25.0,
        "bb_pct": 9.4
      },
      "last5_starts_avg_ip": null,
      "is_opener": false,
      "opener_reason": null,
      "team": "Houston Astros",
      "game_pk": 824849
    },
    "shane baz": {
      "pid": 669358,
      "name": "Shane Baz",
      "hand": "R",
      "vs_r": {
        "tbf": 46,
        "k_pct": 21.7,
        "bb_pct": 2.2,
        "woba": null,
        "hr_per_pa": 2.2,
        "avg_against": ".209",
        "ops_against": ".634"
      },
      "vs_l": {
        "tbf": 80,
        "k_pct": 16.2,
        "bb_pct": 11.2,
        "woba": null,
        "hr_per_pa": 1.2,
        "avg_against": ".373",
        "ops_against": "1.005"
      },
      "season_summary": {
        "games": null,
        "starts": 5,
        "ip": "28.1",
        "era": "5.08",
        "k_pct": 18.3,
        "bb_pct": 7.9
      },
      "last5_starts_avg_ip": 5.48,
      "is_opener": false,
      "opener_reason": null,
      "team": "Baltimore Orioles",
      "game_pk": 824849
    },
    "chase burns": {
      "pid": 695505,
      "name": "Chase Burns",
      "hand": "R",
      "vs_r": {
        "tbf": 47,
        "k_pct": 27.7,
        "bb_pct": 2.1,
        "woba": null,
        "hr_per_pa": 2.1,
        "avg_against": ".152",
        "ops_against": ".409"
      },
      "vs_l": {
        "tbf": 64,
        "k_pct": 26.6,
        "bb_pct": 15.6,
        "woba": null,
        "hr_per_pa": 4.7,
        "avg_against": ".222",
        "ops_against": ".733"
      },
      "season_summary": {
        "games": null,
        "starts": 5,
        "ip": "28.0",
        "era": "2.57",
        "k_pct": 27.0,
        "bb_pct": 9.9
      },
      "last5_starts_avg_ip": 5.46,
      "is_opener": false,
      "opener_reason": null,
      "team": "Cincinnati Reds",
      "game_pk": 824526
    },
    "kyle leahy": {
      "pid": 681517,
      "name": "Kyle Leahy",
      "hand": "R",
      "vs_r": {
        "tbf": 53,
        "k_pct": 15.1,
        "bb_pct": 7.5,
        "woba": null,
        "hr_per_pa": 3.8,
        "avg_against": ".217",
        "ops_against": ".699"
      },
      "vs_l": {
        "tbf": 58,
        "k_pct": 12.1,
        "bb_pct": 12.1,
        "woba": null,
        "hr_per_pa": 3.4,
        "avg_against": ".373",
        "ops_against": "1.017"
      },
      "season_summary": {
        "games": null,
        "starts": 5,
        "ip": "24.0",
        "era": "5.63",
        "k_pct": 13.5,
        "bb_pct": 9.9
      },
      "last5_starts_avg_ip": 4.8,
      "is_opener": false,
      "opener_reason": null,
      "team": "St. Louis Cardinals",
      "game_pk": 823390
    },
    "tyler mahle": {
      "pid": 641816,
      "name": "Tyler Mahle",
      "hand": "R",
      "vs_r": {
        "tbf": 58,
        "k_pct": 20.7,
        "bb_pct": 15.5,
        "woba": null,
        "hr_per_pa": 8.6,
        "avg_against": ".306",
        "ops_against": "1.026"
      },
      "vs_l": {
        "tbf": 56,
        "k_pct": 25.0,
        "bb_pct": 8.9,
        "woba": null,
        "hr_per_pa": 1.8,
        "avg_against": ".240",
        "ops_against": ".669"
      },
      "season_summary": {
        "games": null,
        "starts": 5,
        "ip": "25.2",
        "era": "5.26",
        "k_pct": 22.8,
        "bb_pct": 12.3
      },
      "last5_starts_avg_ip": 5.04,
      "is_opener": false,
      "opener_reason": null,
      "team": "San Francisco Giants",
      "game_pk": 823473
    },
    "jesus luzardo": {
      "pid": 666200,
      "name": "Jes\u00fas Luzardo",
      "hand": "L",
      "vs_r": {
        "tbf": 99,
        "k_pct": 28.3,
        "bb_pct": 8.1,
        "woba": null,
        "hr_per_pa": 2.0,
        "avg_against": ".289",
        "ops_against": ".765"
      },
      "vs_l": {
        "tbf": 23,
        "k_pct": 21.7,
        "bb_pct": 4.3,
        "woba": null,
        "hr_per_pa": 4.3,
        "avg_against": ".318",
        "ops_against": ".803"
      },
      "season_summary": {
        "games": null,
        "starts": 5,
        "ip": "27.1",
        "era": "6.91",
        "k_pct": 27.0,
        "bb_pct": 7.4
      },
      "last5_starts_avg_ip": 5.14,
      "is_opener": false,
      "opener_reason": null,
      "team": "Philadelphia Phillies",
      "game_pk": 823473
    },
    "payton tolle": {
      "pid": 801139,
      "name": "Payton Tolle",
      "hand": "L",
      "vs_r": {
        "tbf": 13,
        "k_pct": 61.5,
        "bb_pct": 7.7,
        "woba": null,
        "hr_per_pa": 0.0,
        "avg_against": ".083",
        "ops_against": ".237"
      },
      "vs_l": {
        "tbf": 9,
        "k_pct": 33.3,
        "bb_pct": 0.0,
        "woba": null,
        "hr_per_pa": 11.1,
        "avg_against": ".222",
        "ops_against": ".778"
      },
      "season_summary": {
        "games": null,
        "starts": 1,
        "ip": "6.0",
        "era": "1.50",
        "k_pct": 50.0,
        "bb_pct": 4.5
      },
      "last5_starts_avg_ip": 6.0,
      "is_opener": false,
      "opener_reason": null,
      "team": "Boston Red Sox",
      "game_pk": 822823
    },
    "trey yesavage": {
      "pid": 702056,
      "name": "Trey Yesavage",
      "hand": "R",
      "vs_r": null,
      "vs_l": null,
      "season_summary": {
        "games": null,
        "starts": null,
        "ip": null,
        "era": null,
        "k_pct": null,
        "bb_pct": null
      },
      "last5_starts_avg_ip": null,
      "is_opener": false,
      "opener_reason": null,
      "team": "Toronto Blue Jays",
      "game_pk": 822823
    },
    "zack littell": {
      "pid": 641793,
      "name": "Zack Littell",
      "hand": "R",
      "vs_r": {
        "tbf": 54,
        "k_pct": 18.5,
        "bb_pct": 5.6,
        "woba": null,
        "hr_per_pa": 3.7,
        "avg_against": ".300",
        "ops_against": ".793"
      },
      "vs_l": {
        "tbf": 63,
        "k_pct": 7.9,
        "bb_pct": 7.9,
        "woba": null,
        "hr_per_pa": 14.3,
        "avg_against": ".328",
        "ops_against": "1.191"
      },
      "season_summary": {
        "games": null,
        "starts": 4,
        "ip": "25.0",
        "era": "7.56",
        "k_pct": 12.8,
        "bb_pct": 6.8
      },
      "last5_starts_avg_ip": 5.0,
      "is_opener": false,
      "opener_reason": null,
      "team": "Washington Nationals",
      "game_pk": 823636
    },
    "clay holmes": {
      "pid": 605280,
      "name": "Clay Holmes",
      "hand": "R",
      "vs_r": {
        "tbf": 50,
        "k_pct": 18.0,
        "bb_pct": 6.0,
        "woba": null,
        "hr_per_pa": 2.0,
        "avg_against": ".196",
        "ops_against": ".521"
      },
      "vs_l": {
        "tbf": 70,
        "k_pct": 14.3,
        "bb_pct": 10.0,
        "woba": null,
        "hr_per_pa": 2.9,
        "avg_against": ".194",
        "ops_against": ".642"
      },
      "season_summary": {
        "games": null,
        "starts": 5,
        "ip": "30.0",
        "era": "2.10",
        "k_pct": 15.8,
        "bb_pct": 8.3
      },
      "last5_starts_avg_ip": 5.86,
      "is_opener": false,
      "opener_reason": null,
      "team": "New York Mets",
      "game_pk": 823636
    },
    "casey mize": {
      "pid": 663554,
      "name": "Casey Mize",
      "hand": "R",
      "vs_r": {
        "tbf": 50,
        "k_pct": 24.0,
        "bb_pct": 10.0,
        "woba": null,
        "hr_per_pa": 4.0,
        "avg_against": ".349",
        "ops_against": "1.071"
      },
      "vs_l": {
        "tbf": 67,
        "k_pct": 29.9,
        "bb_pct": 7.5,
        "woba": null,
        "hr_per_pa": 0.0,
        "avg_against": ".131",
        "ops_against": ".325"
      },
      "season_summary": {
        "games": null,
        "starts": 5,
        "ip": "28.2",
        "era": "2.51",
        "k_pct": 27.4,
        "bb_pct": 8.5
      },
      "last5_starts_avg_ip": 5.5,
      "is_opener": false,
      "opener_reason": null,
      "team": "Detroit Tigers",
      "game_pk": 824931
    },
    "martin perez": {
      "pid": 527048,
      "name": "Mart\u00edn P\u00e9rez",
      "hand": "L",
      "vs_r": {
        "tbf": 64,
        "k_pct": 15.6,
        "bb_pct": 9.4,
        "woba": null,
        "hr_per_pa": 3.1,
        "avg_against": ".161",
        "ops_against": ".559"
      },
      "vs_l": {
        "tbf": 27,
        "k_pct": 14.8,
        "bb_pct": 0.0,
        "woba": null,
        "hr_per_pa": 3.7,
        "avg_against": ".280",
        "ops_against": ".853"
      },
      "season_summary": {
        "games": null,
        "starts": 3,
        "ip": "23.1",
        "era": "2.70",
        "k_pct": 15.4,
        "bb_pct": 6.6
      },
      "last5_starts_avg_ip": 5.33,
      "is_opener": false,
      "opener_reason": null,
      "team": "Atlanta Braves",
      "game_pk": 824931
    },
    "logan gilbert": {
      "pid": 669302,
      "name": "Logan Gilbert",
      "hand": "R",
      "vs_r": {
        "tbf": 57,
        "k_pct": 21.1,
        "bb_pct": 0.0,
        "woba": null,
        "hr_per_pa": 1.8,
        "avg_against": ".286",
        "ops_against": ".762"
      },
      "vs_l": {
        "tbf": 79,
        "k_pct": 29.1,
        "bb_pct": 8.9,
        "woba": null,
        "hr_per_pa": 2.5,
        "avg_against": ".271",
        "ops_against": ".785"
      },
      "season_summary": {
        "games": null,
        "starts": 6,
        "ip": "33.0",
        "era": "4.36",
        "k_pct": 25.7,
        "bb_pct": 5.1
      },
      "last5_starts_avg_ip": 5.44,
      "is_opener": false,
      "opener_reason": null,
      "team": "Seattle Mariners",
      "game_pk": 823716
    },
    "joe ryan": {
      "pid": 657746,
      "name": "Joe Ryan",
      "hand": "R",
      "vs_r": {
        "tbf": 68,
        "k_pct": 27.9,
        "bb_pct": 8.8,
        "woba": null,
        "hr_per_pa": 0.0,
        "avg_against": ".167",
        "ops_against": ".452"
      },
      "vs_l": {
        "tbf": 64,
        "k_pct": 21.9,
        "bb_pct": 3.1,
        "woba": null,
        "hr_per_pa": 4.7,
        "avg_against": ".250",
        "ops_against": ".814"
      },
      "season_summary": {
        "games": null,
        "starts": 6,
        "ip": "32.1",
        "era": "3.90",
        "k_pct": 25.0,
        "bb_pct": 6.1
      },
      "last5_starts_avg_ip": 5.4,
      "is_opener": false,
      "opener_reason": null,
      "team": "Minnesota Twins",
      "game_pk": 823716
    },
    "jose soriano": {
      "pid": 667755,
      "name": "Jos\u00e9 Soriano",
      "hand": "R",
      "vs_r": {
        "tbf": 78,
        "k_pct": 28.2,
        "bb_pct": 10.3,
        "woba": null,
        "hr_per_pa": 0.0,
        "avg_against": ".114",
        "ops_against": ".319"
      },
      "vs_l": {
        "tbf": 62,
        "k_pct": 33.9,
        "bb_pct": 8.1,
        "woba": null,
        "hr_per_pa": 1.6,
        "avg_against": ".179",
        "ops_against": ".496"
      },
      "season_summary": {
        "games": null,
        "starts": 6,
        "ip": "37.2",
        "era": "0.24",
        "k_pct": 30.7,
        "bb_pct": 9.3
      },
      "last5_starts_avg_ip": 6.24,
      "is_opener": false,
      "opener_reason": null,
      "team": "Los Angeles Angels",
      "game_pk": 824610
    },
    "davis martin": {
      "pid": 663436,
      "name": "Davis Martin",
      "hand": "R",
      "vs_r": {
        "tbf": 42,
        "k_pct": 26.2,
        "bb_pct": 2.4,
        "woba": null,
        "hr_per_pa": 0.0,
        "avg_against": ".225",
        "ops_against": ".537"
      },
      "vs_l": {
        "tbf": 76,
        "k_pct": 19.7,
        "bb_pct": 7.9,
        "woba": null,
        "hr_per_pa": 2.6,
        "avg_against": ".229",
        "ops_against": ".689"
      },
      "season_summary": {
        "games": null,
        "starts": 5,
        "ip": "31.1",
        "era": "2.01",
        "k_pct": 22.0,
        "bb_pct": 5.9
      },
      "last5_starts_avg_ip": 6.22,
      "is_opener": false,
      "opener_reason": null,
      "team": "Chicago White Sox",
      "game_pk": 824610
    },
    "chad patrick": {
      "pid": 694477,
      "name": "Chad Patrick",
      "hand": "R",
      "vs_r": {
        "tbf": 46,
        "k_pct": 15.2,
        "bb_pct": 10.9,
        "woba": null,
        "hr_per_pa": 2.2,
        "avg_against": ".171",
        "ops_against": ".554"
      },
      "vs_l": {
        "tbf": 48,
        "k_pct": 8.3,
        "bb_pct": 6.2,
        "woba": null,
        "hr_per_pa": 2.1,
        "avg_against": ".318",
        "ops_against": ".831"
      },
      "season_summary": {
        "games": null,
        "starts": 3,
        "ip": "23.0",
        "era": "2.35",
        "k_pct": 11.7,
        "bb_pct": 8.5
      },
      "last5_starts_avg_ip": 5.1,
      "is_opener": false,
      "opener_reason": null,
      "team": "Milwaukee Brewers",
      "game_pk": 823798
    },
    "cam schlittler": {
      "pid": 693645,
      "name": "Cam Schlittler",
      "hand": "R",
      "vs_r": {
        "tbf": 58,
        "k_pct": 32.8,
        "bb_pct": 3.4,
        "woba": null,
        "hr_per_pa": 1.7,
        "avg_against": ".127",
        "ops_against": ".358"
      },
      "vs_l": {
        "tbf": 75,
        "k_pct": 29.3,
        "bb_pct": 2.7,
        "woba": null,
        "hr_per_pa": 0.0,
        "avg_against": ".205",
        "ops_against": ".515"
      },
      "season_summary": {
        "games": null,
        "starts": 6,
        "ip": "35.2",
        "era": "1.77",
        "k_pct": 30.8,
        "bb_pct": 3.0
      },
      "last5_starts_avg_ip": 6.02,
      "is_opener": false,
      "opener_reason": null,
      "team": "New York Yankees",
      "game_pk": 822908
    },
    "jacob degrom": {
      "pid": 594798,
      "name": "Jacob deGrom",
      "hand": "R",
      "vs_r": {
        "tbf": 33,
        "k_pct": 42.4,
        "bb_pct": 3.0,
        "woba": null,
        "hr_per_pa": 3.0,
        "avg_against": ".344",
        "ops_against": ".833"
      },
      "vs_l": {
        "tbf": 68,
        "k_pct": 30.9,
        "bb_pct": 8.8,
        "woba": null,
        "hr_per_pa": 4.4,
        "avg_against": ".145",
        "ops_against": ".527"
      },
      "season_summary": {
        "games": null,
        "starts": 5,
        "ip": "25.1",
        "era": "2.13",
        "k_pct": 34.7,
        "bb_pct": 6.9
      },
      "last5_starts_avg_ip": 4.88,
      "is_opener": false,
      "opener_reason": null,
      "team": "Texas Rangers",
      "game_pk": 822908
    },
    "kris bubic": {
      "pid": 663460,
      "name": "Kris Bubic",
      "hand": "L",
      "vs_r": {
        "tbf": 91,
        "k_pct": 25.3,
        "bb_pct": 13.2,
        "woba": null,
        "hr_per_pa": 2.2,
        "avg_against": ".203",
        "ops_against": ".662"
      },
      "vs_l": {
        "tbf": 22,
        "k_pct": 27.3,
        "bb_pct": 4.5,
        "woba": null,
        "hr_per_pa": 4.5,
        "avg_against": ".143",
        "ops_against": ".563"
      },
      "season_summary": {
        "games": null,
        "starts": 5,
        "ip": "28.2",
        "era": "4.08",
        "k_pct": 25.7,
        "bb_pct": 11.5
      },
      "last5_starts_avg_ip": 5.64,
      "is_opener": false,
      "opener_reason": null,
      "team": "Kansas City Royals",
      "game_pk": 825017
    },
    "edward cabrera": {
      "pid": 665795,
      "name": "Edward Cabrera",
      "hand": "R",
      "vs_r": {
        "tbf": 49,
        "k_pct": 28.6,
        "bb_pct": 4.1,
        "woba": null,
        "hr_per_pa": 0.0,
        "avg_against": ".191",
        "ops_against": ".479"
      },
      "vs_l": {
        "tbf": 70,
        "k_pct": 11.4,
        "bb_pct": 12.9,
        "woba": null,
        "hr_per_pa": 2.9,
        "avg_against": ".259",
        "ops_against": ".745"
      },
      "season_summary": {
        "games": null,
        "starts": 5,
        "ip": "29.2",
        "era": "2.73",
        "k_pct": 18.5,
        "bb_pct": 9.2
      },
      "last5_starts_avg_ip": 5.84,
      "is_opener": false,
      "opener_reason": null,
      "team": "Chicago Cubs",
      "game_pk": 823310
    },
    "walker buehler": {
      "pid": 621111,
      "name": "Walker Buehler",
      "hand": "R",
      "vs_r": {
        "tbf": 36,
        "k_pct": 25.0,
        "bb_pct": 8.3,
        "woba": null,
        "hr_per_pa": 2.8,
        "avg_against": ".219",
        "ops_against": ".681"
      },
      "vs_l": {
        "tbf": 56,
        "k_pct": 19.6,
        "bb_pct": 10.7,
        "woba": null,
        "hr_per_pa": 0.0,
        "avg_against": ".340",
        "ops_against": ".831"
      },
      "season_summary": {
        "games": null,
        "starts": 5,
        "ip": "20.1",
        "era": "5.75",
        "k_pct": 21.7,
        "bb_pct": 9.8
      },
      "last5_starts_avg_ip": 3.88,
      "is_opener": false,
      "opener_reason": null,
      "team": "San Diego Padres",
      "game_pk": 823310
    },
    "janson junk": {
      "pid": 676083,
      "name": "Janson Junk",
      "hand": "R",
      "vs_r": {
        "tbf": 50,
        "k_pct": 14.0,
        "bb_pct": 6.0,
        "woba": null,
        "hr_per_pa": 2.0,
        "avg_against": ".109",
        "ops_against": ".359"
      },
      "vs_l": {
        "tbf": 60,
        "k_pct": 16.7,
        "bb_pct": 6.7,
        "woba": null,
        "hr_per_pa": 1.7,
        "avg_against": ".345",
        "ops_against": ".891"
      },
      "season_summary": {
        "games": null,
        "starts": 5,
        "ip": "27.0",
        "era": "3.67",
        "k_pct": 15.5,
        "bb_pct": 6.4
      },
      "last5_starts_avg_ip": 5.26,
      "is_opener": false,
      "opener_reason": null,
      "team": "Miami Marlins",
      "game_pk": 823956
    },
    "shohei ohtani": {
      "pid": 660271,
      "name": "Shohei Ohtani",
      "hand": "R",
      "vs_r": {
        "tbf": 40,
        "k_pct": 37.5,
        "bb_pct": 7.5,
        "woba": null,
        "hr_per_pa": 0.0,
        "avg_against": ".162",
        "ops_against": ".441"
      },
      "vs_l": {
        "tbf": 52,
        "k_pct": 19.2,
        "bb_pct": 5.8,
        "woba": null,
        "hr_per_pa": 0.0,
        "avg_against": ".125",
        "ops_against": ".400"
      },
      "season_summary": {
        "games": null,
        "starts": 4,
        "ip": "24.0",
        "era": "0.38",
        "k_pct": 27.2,
        "bb_pct": 6.5
      },
      "last5_starts_avg_ip": 6.0,
      "is_opener": false,
      "opener_reason": null,
      "team": "Los Angeles Dodgers",
      "game_pk": 823956
    }
  }
}