{
  "generated_at": "2026-04-27",
  "source": "UmpScorecards (umpscorecards.com/api)",
  "source_url": "https://umpscorecards.com",
  "methodology": "Per-ump: 2024x1 + 2025x2 + 2026x2 weighted, 50-game Bayesian prior. Baseline = 2025+2026 game-weighted mean.",
  "window_label": "2024-2026 (2025/26 double-weighted)",
  "shrinkage_prior_games": 50,
  "baseline": 0.3655730809674026,
  "league_avg": {
    "baseline_off_adj": 0.3656,
    "acc_above_x_mean": 0.6435
  },
  "umpires": {
    "Lance Barksdale": {
      "n": 70,
      "off_adj_shrunk": 0.6624,
      "off_adj_raw": 0.874,
      "acc_above_x": 0.583
    },
    "Andy Fletcher": {
      "n": 68,
      "off_adj_shrunk": 0.3727,
      "off_adj_raw": 0.378,
      "acc_above_x": -0.626
    },
    "Adrian Johnson": {
      "n": 69,
      "off_adj_shrunk": 0.4037,
      "off_adj_raw": 0.431,
      "acc_above_x": -0.094
    },
    "Dan Iassogna": {
      "n": 68,
      "off_adj_shrunk": 0.1649,
      "off_adj_raw": 0.017,
      "acc_above_x": -0.045
    },
    "Mark Ripperger": {
      "n": 71,
      "off_adj_shrunk": 0.1675,
      "off_adj_raw": 0.028,
      "acc_above_x": 1.736
    },
    "Alan Porter": {
      "n": 66,
      "off_adj_shrunk": 0.4769,
      "off_adj_raw": 0.561,
      "acc_above_x": 1.857
    },
    "Todd Tichenor": {
      "n": 67,
      "off_adj_shrunk": 0.446,
      "off_adj_raw": 0.506,
      "acc_above_x": 0.661
    },
    "Laz Diaz": {
      "n": 67,
      "off_adj_shrunk": 0.2661,
      "off_adj_raw": 0.192,
      "acc_above_x": -0.581
    },
    "Brian O'Nora": {
      "n": 60,
      "off_adj_shrunk": -0.0329,
      "off_adj_raw": -0.365,
      "acc_above_x": -0.325
    },
    "Chris Guccione": {
      "n": 53,
      "off_adj_shrunk": 0.5561,
      "off_adj_raw": 0.736,
      "acc_above_x": 0.79
    },
    "James Hoye": {
      "n": 67,
      "off_adj_shrunk": 0.3995,
      "off_adj_raw": 0.425,
      "acc_above_x": 0.126
    },
    "Chad Fairchild": {
      "n": 61,
      "off_adj_shrunk": 0.512,
      "off_adj_raw": 0.632,
      "acc_above_x": 0.649
    },
    "Marvin Hudson": {
      "n": 62,
      "off_adj_shrunk": 0.1554,
      "off_adj_raw": -0.014,
      "acc_above_x": 0.057
    },
    "Dan Bellino": {
      "n": 67,
      "off_adj_shrunk": 0.1436,
      "off_adj_raw": -0.022,
      "acc_above_x": 0.69
    },
    "Larry Vanover": {
      "n": 28,
      "off_adj_shrunk": 0.0249,
      "off_adj_raw": -0.584,
      "acc_above_x": -1.376
    },
    "Alfonso M\u00e1rquez": {
      "n": 67,
      "off_adj_shrunk": 0.6861,
      "off_adj_raw": 0.925,
      "acc_above_x": 0.058
    },
    "Mark Wegner": {
      "n": 60,
      "off_adj_shrunk": 0.4732,
      "off_adj_raw": 0.563,
      "acc_above_x": 1.016
    },
    "Cory Blaser": {
      "n": 62,
      "off_adj_shrunk": 0.2131,
      "off_adj_raw": 0.09,
      "acc_above_x": 0.406
    },
    "Brian Knight": {
      "n": 16,
      "off_adj_shrunk": 0.3091,
      "off_adj_raw": 0.132,
      "acc_above_x": 1.122
    },
    "Rob Drake": {
      "n": 38,
      "off_adj_shrunk": -0.0418,
      "off_adj_raw": -0.578,
      "acc_above_x": -0.739
    },
    "Phil Cuzzi": {
      "n": 61,
      "off_adj_shrunk": 0.0873,
      "off_adj_raw": -0.141,
      "acc_above_x": 0.625
    },
    "Hunter Wendelstedt": {
      "n": 39,
      "off_adj_shrunk": 0.2293,
      "off_adj_raw": 0.055,
      "acc_above_x": -1.143
    },
    "David Rackley": {
      "n": 69,
      "off_adj_shrunk": 0.2282,
      "off_adj_raw": 0.129,
      "acc_above_x": 0.52
    },
    "Adam Hamari": {
      "n": 70,
      "off_adj_shrunk": 0.1806,
      "off_adj_raw": 0.048,
      "acc_above_x": 1.56
    },
    "Ryan Blakney": {
      "n": 62,
      "off_adj_shrunk": 0.185,
      "off_adj_raw": 0.039,
      "acc_above_x": 0.764
    },
    "Lance Barrett": {
      "n": 70,
      "off_adj_shrunk": 0.2666,
      "off_adj_raw": 0.196,
      "acc_above_x": 0.247
    },
    "Mark Carlson": {
      "n": 36,
      "off_adj_shrunk": 0.4441,
      "off_adj_raw": 0.553,
      "acc_above_x": 0.192
    },
    "Scott Barry": {
      "n": 56,
      "off_adj_shrunk": 0.4931,
      "off_adj_raw": 0.607,
      "acc_above_x": 0.338
    },
    "Bruce Dreckman": {
      "n": 57,
      "off_adj_shrunk": 0.1504,
      "off_adj_raw": -0.038,
      "acc_above_x": -0.348
    },
    "John Tumpane": {
      "n": 63,
      "off_adj_shrunk": 0.2181,
      "off_adj_raw": 0.101,
      "acc_above_x": 0.57
    },
    "CB Bucknor": {
      "n": 58,
      "off_adj_shrunk": 0.0805,
      "off_adj_raw": -0.165,
      "acc_above_x": -0.688
    },
    "Manny Gonzalez": {
      "n": 57,
      "off_adj_shrunk": 0.4145,
      "off_adj_raw": 0.457,
      "acc_above_x": 0.458
    },
    "Tripp Gibson": {
      "n": 60,
      "off_adj_shrunk": 0.2042,
      "off_adj_raw": 0.07,
      "acc_above_x": 0.96
    },
    "Gabe Morales": {
      "n": 69,
      "off_adj_shrunk": 0.0101,
      "off_adj_raw": -0.248,
      "acc_above_x": 0.809
    },
    "Carlos Torres": {
      "n": 66,
      "off_adj_shrunk": 0.6411,
      "off_adj_raw": 0.85,
      "acc_above_x": 0.605
    },
    "Vic Carapazza": {
      "n": 73,
      "off_adj_shrunk": 0.1407,
      "off_adj_raw": -0.013,
      "acc_above_x": 1.001
    },
    "D.J. Reyburn": {
      "n": 65,
      "off_adj_shrunk": 0.1261,
      "off_adj_raw": -0.058,
      "acc_above_x": 0.662
    },
    "Tony Randazzo": {
      "n": 57,
      "off_adj_shrunk": 0.1907,
      "off_adj_raw": 0.037,
      "acc_above_x": 0.507
    },
    "Nate Tomlinson": {
      "n": 61,
      "off_adj_shrunk": 0.3944,
      "off_adj_raw": 0.418,
      "acc_above_x": 1.527
    },
    "Quinn Wolcott": {
      "n": 67,
      "off_adj_shrunk": 0.4367,
      "off_adj_raw": 0.49,
      "acc_above_x": 1.372
    },
    "Ramon De Jesus": {
      "n": 64,
      "off_adj_shrunk": 0.2145,
      "off_adj_raw": 0.096,
      "acc_above_x": 0.79
    },
    "Jeremie Rehak": {
      "n": 61,
      "off_adj_shrunk": 0.1797,
      "off_adj_raw": 0.027,
      "acc_above_x": 1.502
    },
    "Adam Beck": {
      "n": 69,
      "off_adj_shrunk": 0.3027,
      "off_adj_raw": 0.257,
      "acc_above_x": 1.368
    },
    "Derek Thomas": {
      "n": 58,
      "off_adj_shrunk": 0.2652,
      "off_adj_raw": 0.179,
      "acc_above_x": 1.921
    },
    "Ryan Additon": {
      "n": 66,
      "off_adj_shrunk": 0.2562,
      "off_adj_raw": 0.173,
      "acc_above_x": 0.672
    },
    "Jonathan Parra": {
      "n": 27,
      "off_adj_shrunk": 0.4187,
      "off_adj_raw": 0.517,
      "acc_above_x": 0.144
    },
    "Mike Estabrook": {
      "n": 67,
      "off_adj_shrunk": 0.0593,
      "off_adj_raw": -0.169,
      "acc_above_x": 0.034
    },
    "Dan Merzel": {
      "n": 63,
      "off_adj_shrunk": 0.2776,
      "off_adj_raw": 0.208,
      "acc_above_x": 1.442
    },
    "John Libka": {
      "n": 68,
      "off_adj_shrunk": 0.3838,
      "off_adj_raw": 0.397,
      "acc_above_x": 1.466
    },
    "Nestor Ceja": {
      "n": 64,
      "off_adj_shrunk": 0.2574,
      "off_adj_raw": 0.173,
      "acc_above_x": 1.407
    },
    "Nick Mahrley": {
      "n": 60,
      "off_adj_shrunk": 0.1921,
      "off_adj_raw": 0.048,
      "acc_above_x": 0.878
    },
    "Alex Tosi": {
      "n": 66,
      "off_adj_shrunk": 0.0662,
      "off_adj_raw": -0.161,
      "acc_above_x": 1.578
    },
    "Chris Segal": {
      "n": 67,
      "off_adj_shrunk": 0.2463,
      "off_adj_raw": 0.157,
      "acc_above_x": -0.073
    },
    "Edwin Moscoso": {
      "n": 70,
      "off_adj_shrunk": 0.5059,
      "off_adj_raw": 0.606,
      "acc_above_x": 1.912
    },
    "Sean Barber": {
      "n": 61,
      "off_adj_shrunk": 0.3733,
      "off_adj_raw": 0.38,
      "acc_above_x": 0.361
    },
    "Erich Bacchus": {
      "n": 62,
      "off_adj_shrunk": 0.4052,
      "off_adj_raw": 0.437,
      "acc_above_x": 0.654
    },
    "Ben May": {
      "n": 62,
      "off_adj_shrunk": 0.183,
      "off_adj_raw": 0.036,
      "acc_above_x": 1.126
    },
    "Brennan Miller": {
      "n": 64,
      "off_adj_shrunk": 0.3488,
      "off_adj_raw": 0.336,
      "acc_above_x": 0.271
    },
    "Bill Miller": {
      "n": 71,
      "off_adj_shrunk": -0.1969,
      "off_adj_raw": -0.593,
      "acc_above_x": 0.577
    },
    "Jordan Baker": {
      "n": 66,
      "off_adj_shrunk": 0.2405,
      "off_adj_raw": 0.146,
      "acc_above_x": 0.576
    },
    "Roberto Ortiz": {
      "n": 63,
      "off_adj_shrunk": 0.3898,
      "off_adj_raw": 0.409,
      "acc_above_x": -0.03
    },
    "Charlie Ramos": {
      "n": 67,
      "off_adj_shrunk": 0.3627,
      "off_adj_raw": 0.361,
      "acc_above_x": 0.305
    },
    "Clint Vondrak": {
      "n": 64,
      "off_adj_shrunk": 0.4909,
      "off_adj_raw": 0.589,
      "acc_above_x": 0.97
    },
    "Doug Eddings": {
      "n": 73,
      "off_adj_shrunk": -0.0972,
      "off_adj_raw": -0.414,
      "acc_above_x": 0.324
    },
    "Stu Scheurwater": {
      "n": 66,
      "off_adj_shrunk": 0.1459,
      "off_adj_raw": -0.021,
      "acc_above_x": 0.414
    },
    "Tom Hanahan": {
      "n": 60,
      "off_adj_shrunk": 0.2644,
      "off_adj_raw": 0.18,
      "acc_above_x": 0.424
    },
    "Paul Clemons": {
      "n": 65,
      "off_adj_shrunk": 0.1135,
      "off_adj_raw": -0.08,
      "acc_above_x": 0.68
    },
    "Brian Walsh": {
      "n": 68,
      "off_adj_shrunk": 0.1975,
      "off_adj_raw": 0.074,
      "acc_above_x": 0.408
    },
    "Chad Whitson": {
      "n": 53,
      "off_adj_shrunk": 0.3477,
      "off_adj_raw": 0.331,
      "acc_above_x": 0.515
    },
    "Mike Muchlinski": {
      "n": 65,
      "off_adj_shrunk": 0.1949,
      "off_adj_raw": 0.064,
      "acc_above_x": 0.143
    },
    "Nic Lentz": {
      "n": 65,
      "off_adj_shrunk": 0.484,
      "off_adj_raw": 0.575,
      "acc_above_x": 0.874
    },
    "Jansen Visconti": {
      "n": 66,
      "off_adj_shrunk": 0.3063,
      "off_adj_raw": 0.261,
      "acc_above_x": 1.317
    },
    "Malachi Moore": {
      "n": 65,
      "off_adj_shrunk": 0.151,
      "off_adj_raw": -0.014,
      "acc_above_x": 0.295
    },
    "Emil Jimenez": {
      "n": 66,
      "off_adj_shrunk": 0.0076,
      "off_adj_raw": -0.264,
      "acc_above_x": 1.086
    },
    "Brock Ballou": {
      "n": 38,
      "off_adj_shrunk": 0.4502,
      "off_adj_raw": 0.562,
      "acc_above_x": 0.799
    },
    "Alex MacKay": {
      "n": 61,
      "off_adj_shrunk": 0.2901,
      "off_adj_raw": 0.228,
      "acc_above_x": 1.167
    },
    "Junior Valentine": {
      "n": 55,
      "off_adj_shrunk": 0.4467,
      "off_adj_raw": 0.52,
      "acc_above_x": 1.23
    },
    "John Bacon": {
      "n": 56,
      "off_adj_shrunk": -0.0436,
      "off_adj_raw": -0.409,
      "acc_above_x": 0.366
    },
    "David Arrieta": {
      "n": 13,
      "off_adj_shrunk": 0.3768,
      "off_adj_raw": 0.42,
      "acc_above_x": 0.243
    },
    "Ryan Wills": {
      "n": 63,
      "off_adj_shrunk": 0.3033,
      "off_adj_raw": 0.254,
      "acc_above_x": 0.584
    },
    "Jim Wolf": {
      "n": 58,
      "off_adj_shrunk": 0.213,
      "off_adj_raw": 0.082,
      "acc_above_x": 0.354
    },
    "Edwin Jimenez": {
      "n": 51,
      "off_adj_shrunk": 0.3712,
      "off_adj_raw": 0.377,
      "acc_above_x": 1.64
    },
    "Chris Conroy": {
      "n": 58,
      "off_adj_shrunk": 0.3052,
      "off_adj_raw": 0.253,
      "acc_above_x": 0.856
    },
    "Jeremy Riggs": {
      "n": 17,
      "off_adj_shrunk": 0.166,
      "off_adj_raw": -0.421,
      "acc_above_x": 1.633
    },
    "Will Little": {
      "n": 56,
      "off_adj_shrunk": 0.381,
      "off_adj_raw": 0.395,
      "acc_above_x": 1.342
    },
    "Jacob Metz": {
      "n": 31,
      "off_adj_shrunk": 0.2878,
      "off_adj_raw": 0.162,
      "acc_above_x": 0.783
    },
    "James Jean": {
      "n": 32,
      "off_adj_shrunk": 0.5947,
      "off_adj_raw": 0.953,
      "acc_above_x": 0.787
    },
    "Austin Jones": {
      "n": 39,
      "off_adj_shrunk": 0.3837,
      "off_adj_raw": 0.407,
      "acc_above_x": 1.602
    },
    "Shane Livensparger": {
      "n": 42,
      "off_adj_shrunk": 0.4644,
      "off_adj_raw": 0.582,
      "acc_above_x": 1.181
    },
    "Ron Kulpa": {
      "n": 25,
      "off_adj_shrunk": -0.0166,
      "off_adj_raw": -0.781,
      "acc_above_x": -0.474
    },
    "Willie Traynor": {
      "n": 20,
      "off_adj_shrunk": 0.6174,
      "off_adj_raw": 1.247,
      "acc_above_x": 1.629
    }
  }
}