{
  "generated_at": "2026-04-22T23:06:49+00:00",
  "window_date": "2026-04-06",
  "status": "ok",
  "n_games": 13,
  "games": {
    "823002": {
      "n_sims": 10000,
      "away_team": "Chicago Cubs",
      "home_team": "Tampa Bay Rays",
      "actual_away_runs": 4,
      "actual_home_runs": 6,
      "sim_away_mean": 8.023579,
      "sim_home_mean": 8.235066000000002,
      "sim_away_median": 7.999999999999999,
      "sim_home_median": 8.260000000000003,
      "away_win_prob": 0.46065,
      "home_win_prob": 0.53935,
      "p_away_wins_exactly": 0.4606,
      "p_home_wins_exactly": 0.5393,
      "p_tied": 0.0001,
      "ump_favor_away_runs": 0.0,
      "ump_favor_home_runs": 0.0,
      "ump_adjusted_away_mean": 8.023579,
      "ump_adjusted_home_mean": 8.235066000000002,
      "ump_adjusted_away_wp": 0.46065,
      "ump_adjusted_home_wp": 0.53935,
      "wp_shift_away": 0.0,
      "umpire_name": "Brian Walsh",
      "venue": "Tropicana Field",
      "n_batted_balls": 49
    },
    "824456": {
      "n_sims": 10000,
      "away_team": "Kansas City Royals",
      "home_team": "Cleveland Guardians",
      "actual_away_runs": 4,
      "actual_home_runs": 2,
      "sim_away_mean": 5.932235000000002,
      "sim_home_mean": 5.649926,
      "sim_away_median": 5.935000000000003,
      "sim_home_median": 5.620000000000001,
      "away_win_prob": 0.5467500000000001,
      "home_win_prob": 0.45324999999999993,
      "p_away_wins_exactly": 0.5461,
      "p_home_wins_exactly": 0.4526,
      "p_tied": 0.0013,
      "ump_favor_away_runs": 0.0,
      "ump_favor_home_runs": 0.0,
      "ump_adjusted_away_mean": 5.932235000000002,
      "ump_adjusted_home_mean": 5.649926,
      "ump_adjusted_away_wp": 0.5467500000000001,
      "ump_adjusted_home_wp": 0.45324999999999993,
      "wp_shift_away": 0.0,
      "umpire_name": "Adam Beck",
      "venue": "Progressive Field",
      "n_batted_balls": 53
    },
    "823401": {
      "n_sims": 10000,
      "away_team": "San Diego Padres",
      "home_team": "Pittsburgh Pirates",
      "actual_away_runs": 5,
      "actual_home_runs": 0,
      "sim_away_mean": 6.383879000000001,
      "sim_home_mean": 3.4943209999999993,
      "sim_away_median": 6.379999999999999,
      "sim_home_median": 3.4299999999999993,
      "away_win_prob": 0.89895,
      "home_win_prob": 0.10104999999999997,
      "p_away_wins_exactly": 0.8989,
      "p_home_wins_exactly": 0.101,
      "p_tied": 0.0001,
      "ump_favor_away_runs": 0.0,
      "ump_favor_home_runs": 0.0,
      "ump_adjusted_away_mean": 6.383879000000001,
      "ump_adjusted_home_mean": 3.4943209999999993,
      "ump_adjusted_away_wp": 0.89895,
      "ump_adjusted_home_wp": 0.10104999999999997,
      "wp_shift_away": 0.0,
      "umpire_name": "Tripp Gibson",
      "venue": "PNC Park",
      "n_batted_balls": 53
    },
    "823886": {
      "n_sims": 10000,
      "away_team": "Cincinnati Reds",
      "home_team": "Miami Marlins",
      "actual_away_runs": 2,
      "actual_home_runs": 0,
      "sim_away_mean": 5.670710999999999,
      "sim_home_mean": 4.806042,
      "sim_away_median": 5.620000000000001,
      "sim_home_median": 4.8,
      "away_win_prob": 0.6492500000000001,
      "home_win_prob": 0.3507499999999999,
      "p_away_wins_exactly": 0.6487,
      "p_home_wins_exactly": 0.3502,
      "p_tied": 0.0011,
      "ump_favor_away_runs": 0.0,
      "ump_favor_home_runs": 0.0,
      "ump_adjusted_away_mean": 5.670710999999999,
      "ump_adjusted_home_mean": 4.806042,
      "ump_adjusted_away_wp": 0.6492500000000001,
      "ump_adjusted_home_wp": 0.3507499999999999,
      "wp_shift_away": 0.0,
      "umpire_name": "John Libka",
      "venue": "loanDepot park",
      "n_batted_balls": 52
    },
    "822755": {
      "n_sims": 10000,
      "away_team": "St. Louis Cardinals",
      "home_team": "Washington Nationals",
      "actual_away_runs": 6,
      "actual_home_runs": 9,
      "sim_away_mean": 8.064485999999999,
      "sim_home_mean": 10.484384,
      "sim_away_median": 8.07,
      "sim_home_median": 10.5,
      "away_win_prob": 0.1853,
      "home_win_prob": 0.8147,
      "p_away_wins_exactly": 0.1852,
      "p_home_wins_exactly": 0.8146,
      "p_tied": 0.0002,
      "ump_favor_away_runs": 0.0,
      "ump_favor_home_runs": 0.0,
      "ump_adjusted_away_mean": 8.064485999999999,
      "ump_adjusted_home_mean": 10.484384,
      "ump_adjusted_away_wp": 0.1853,
      "ump_adjusted_home_wp": 0.8147,
      "wp_shift_away": 0.0,
      "umpire_name": "Tom Hanahan",
      "venue": "Nationals Park",
      "n_batted_balls": 58
    },
    "824783": {
      "n_sims": 10000,
      "away_team": "Milwaukee Brewers",
      "home_team": "Boston Red Sox",
      "actual_away_runs": 8,
      "actual_home_runs": 6,
      "sim_away_mean": 9.393434000000001,
      "sim_home_mean": 9.053422,
      "sim_away_median": 9.43,
      "sim_home_median": 9.12,
      "away_win_prob": 0.5527,
      "home_win_prob": 0.44730000000000003,
      "p_away_wins_exactly": 0.5497,
      "p_home_wins_exactly": 0.4443,
      "p_tied": 0.006,
      "ump_favor_away_runs": 0.0,
      "ump_favor_home_runs": 0.0,
      "ump_adjusted_away_mean": 9.393434000000001,
      "ump_adjusted_home_mean": 9.053422,
      "ump_adjusted_away_wp": 0.5527,
      "ump_adjusted_home_wp": 0.44730000000000003,
      "wp_shift_away": 0.0,
      "umpire_name": "Chris Conroy",
      "venue": "Fenway Park",
      "n_batted_balls": 60
    },
    "822832": {
      "n_sims": 10000,
      "away_team": "Los Angeles Dodgers",
      "home_team": "Toronto Blue Jays",
      "actual_away_runs": 14,
      "actual_home_runs": 2,
      "sim_away_mean": 12.884839999999999,
      "sim_home_mean": 6.901703999999998,
      "sim_away_median": 12.879999999999999,
      "sim_home_median": 6.929999999999999,
      "away_win_prob": 0.9829,
      "home_win_prob": 0.017100000000000004,
      "p_away_wins_exactly": 0.9829,
      "p_home_wins_exactly": 0.0171,
      "p_tied": 0.0,
      "ump_favor_away_runs": 0.0,
      "ump_favor_home_runs": 0.0,
      "ump_adjusted_away_mean": 12.884839999999999,
      "ump_adjusted_home_mean": 6.901703999999998,
      "ump_adjusted_away_wp": 0.9829,
      "ump_adjusted_home_wp": 0.017100000000000004,
      "wp_shift_away": 0.0,
      "umpire_name": "Shane Livensparger",
      "venue": "Rogers Centre",
      "n_batted_balls": 62
    },
    "823728": {
      "n_sims": 10000,
      "away_team": "Detroit Tigers",
      "home_team": "Minnesota Twins",
      "actual_away_runs": 3,
      "actual_home_runs": 7,
      "sim_away_mean": 5.711084,
      "sim_home_mean": 7.400056,
      "sim_away_median": 5.6899999999999995,
      "sim_home_median": 7.380000000000001,
      "away_win_prob": 0.21345,
      "home_win_prob": 0.78655,
      "p_away_wins_exactly": 0.2133,
      "p_home_wins_exactly": 0.7864,
      "p_tied": 0.0003,
      "ump_favor_away_runs": 0.0,
      "ump_favor_home_runs": 0.0,
      "ump_adjusted_away_mean": 5.711084,
      "ump_adjusted_home_mean": 7.400056,
      "ump_adjusted_away_wp": 0.21345,
      "ump_adjusted_home_wp": 0.78655,
      "wp_shift_away": 0.0,
      "umpire_name": "Rob Drake",
      "venue": "Target Field",
      "n_batted_balls": 45
    },
    "824619": {
      "n_sims": 10000,
      "away_team": "Baltimore Orioles",
      "home_team": "Chicago White Sox",
      "actual_away_runs": 2,
      "actual_home_runs": 1,
      "sim_away_mean": 4.981371,
      "sim_home_mean": 5.755084,
      "sim_away_median": 4.930000000000001,
      "sim_home_median": 5.739999999999998,
      "away_win_prob": 0.36924999999999997,
      "home_win_prob": 0.63075,
      "p_away_wins_exactly": 0.368,
      "p_home_wins_exactly": 0.6295,
      "p_tied": 0.0025,
      "ump_favor_away_runs": 0.0,
      "ump_favor_home_runs": 0.0,
      "ump_adjusted_away_mean": 4.981371,
      "ump_adjusted_home_mean": 5.755084,
      "ump_adjusted_away_wp": 0.36924999999999997,
      "ump_adjusted_home_wp": 0.63075,
      "wp_shift_away": 0.0,
      "umpire_name": "Malachi Moore",
      "venue": "Rate Field",
      "n_batted_balls": 47
    },
    "822918": {
      "n_sims": 10000,
      "away_team": "Seattle Mariners",
      "home_team": "Texas Rangers",
      "actual_away_runs": 1,
      "actual_home_runs": 2,
      "sim_away_mean": 5.294678,
      "sim_home_mean": 3.881426999999999,
      "sim_away_median": 5.309999999999999,
      "sim_home_median": 3.879999999999998,
      "away_win_prob": 0.7389,
      "home_win_prob": 0.2611,
      "p_away_wins_exactly": 0.7379,
      "p_home_wins_exactly": 0.2601,
      "p_tied": 0.002,
      "ump_favor_away_runs": 0.0,
      "ump_favor_home_runs": 0.0,
      "ump_adjusted_away_mean": 5.294678,
      "ump_adjusted_home_mean": 3.881426999999999,
      "ump_adjusted_away_wp": 0.7389,
      "ump_adjusted_home_wp": 0.2611,
      "wp_shift_away": 0.0,
      "umpire_name": "Alex MacKay",
      "venue": "Globe Life Field",
      "n_batted_balls": 43
    },
    "824376": {
      "n_sims": 10000,
      "away_team": "Houston Astros",
      "home_team": "Colorado Rockies",
      "actual_away_runs": 7,
      "actual_home_runs": 9,
      "sim_away_mean": 10.581337000000003,
      "sim_home_mean": 10.416439000000002,
      "sim_away_median": 10.610000000000003,
      "sim_home_median": 10.440000000000001,
      "away_win_prob": 0.5223500000000001,
      "home_win_prob": 0.4776499999999999,
      "p_away_wins_exactly": 0.5218,
      "p_home_wins_exactly": 0.4771,
      "p_tied": 0.0011,
      "ump_favor_away_runs": 0.0,
      "ump_favor_home_runs": 0.0,
      "ump_adjusted_away_mean": 10.581337000000003,
      "ump_adjusted_home_mean": 10.416439000000002,
      "ump_adjusted_away_wp": 0.5223500000000001,
      "ump_adjusted_home_wp": 0.4776499999999999,
      "wp_shift_away": 0.0,
      "umpire_name": "Nestor Ceja",
      "venue": "Coors Field",
      "n_batted_balls": 63
    },
    "824052": {
      "n_sims": 10000,
      "away_team": "Atlanta Braves",
      "home_team": "Los Angeles Angels",
      "actual_away_runs": 2,
      "actual_home_runs": 6,
      "sim_away_mean": 4.5883899999999995,
      "sim_home_mean": 7.532920999999999,
      "sim_away_median": 4.619999999999997,
      "sim_home_median": 7.5,
      "away_win_prob": 0.0942,
      "home_win_prob": 0.9057999999999999,
      "p_away_wins_exactly": 0.0942,
      "p_home_wins_exactly": 0.9058,
      "p_tied": 0.0,
      "ump_favor_away_runs": 0.0,
      "ump_favor_home_runs": 0.0,
      "ump_adjusted_away_mean": 4.5883899999999995,
      "ump_adjusted_home_mean": 7.532920999999999,
      "ump_adjusted_away_wp": 0.0942,
      "ump_adjusted_home_wp": 0.9057999999999999,
      "wp_shift_away": 0.0,
      "umpire_name": "Hunter Wendelstedt",
      "venue": "Angel Stadium",
      "n_batted_balls": 38
    },
    "823237": {
      "n_sims": 10000,
      "away_team": "Philadelphia Phillies",
      "home_team": "San Francisco Giants",
      "actual_away_runs": 6,
      "actual_home_runs": 4,
      "sim_away_mean": 7.572452,
      "sim_home_mean": 5.746920000000002,
      "sim_away_median": 7.500000000000001,
      "sim_home_median": 5.75,
      "away_win_prob": 0.77705,
      "home_win_prob": 0.22294999999999998,
      "p_away_wins_exactly": 0.777,
      "p_home_wins_exactly": 0.2229,
      "p_tied": 0.0001,
      "ump_favor_away_runs": 0.0,
      "ump_favor_home_runs": 0.0,
      "ump_adjusted_away_mean": 7.572452,
      "ump_adjusted_home_mean": 5.746920000000002,
      "ump_adjusted_away_wp": 0.77705,
      "ump_adjusted_home_wp": 0.22294999999999998,
      "wp_shift_away": 0.0,
      "umpire_name": "Adam Hamari",
      "venue": "Oracle Park",
      "n_batted_balls": 59
    }
  }
}